groupie/__init__.py
groupie/py.typed
groupie-0.2.1.dist-info/METADATA
groupie-0.2.1.dist-info/WHEEL
groupie-0.2.1.dist-info/licenses/LICENSE
groupie-0.2.1.dist-info/RECORD
