Metadata-Version: 2.4
Name: groupie
Version: 0.2.1
Summary: Exception group utilities for exceptional code
License-File: LICENSE
Requires-Python: >=3.13
